typograf-0.1.1.dist-info/RECORD
typograf-0.1.1.dist-info/WHEEL
typograf-0.1.1.dist-info/METADATA
typograf-0.1.1.dist-info/metadata.json
typograf-0.1.1.dist-info/top_level.txt
typograf-0.1.1.dist-info/DESCRIPTION.rst
typograf/__init__.py
typograf/remote_typograf.py
