Metadata-Version: 2.0
Name: typograf
Version: 0.1.1
Summary: Client for atrlebedev typograf service
Home-page: https://github.com/Samael500/typograf
Author: Maksim Skorokhod
Author-email: Samael500@gmail.com
License: MIT
Platform: UNKNOWN
